Workbook

Sheet Source Data
A1: Invoice ID | B1: Branch | C1: City | D1: Customer type | E1: Gender | F1: Product line | G1: Unit price | H1: Quantity | I1: Tax 5% | J1: Total | K1: Date | L1: Time | M1: Payment | N1: cogs | O1: gross margin percentage | P1: gross income | Q1: Rating
A2: 750-67-8428 | B2: A | C2: Yangon | D2: Member | E2: Female | F2: Health and beauty | G2: 74.69 | H2: 7 | I2: 26.1415 | J2: 548.9715 | K2: 43470 | L2: 0.54722222 | M2: Ewallet | N2: 522.83 | O2: 4.7619048 | P2: 26.1415 | Q2: 9.1
A3: 226-31-3081 | B3: C | C3: Naypyitaw | D3: Normal | E3: Female | F3: Electronic accessories | G3: 15.28 | H3: 5 | I3: 3.82 | J3: 80.22 | K3: 43532 | L3: 0.43680556 | M3: Cash | N3: 76.4 | O3: 4.7619048 | P3: 3.82 | Q3: 9.6
A4: 631-41-3108 | B4: A | C4: Yangon | D4: Normal | E4: Male | F4: Home and lifestyle | G4: 46.33 | H4: 7 | I4: 16.2155 | J4: 340.5255 | K4: 43527 | L4: 0.55763889 | M4: Credit card | N4: 324.31 | O4: 4.7619048 | P4: 16.2155 | Q4: 7.4
A5: 123-19-1176 | B5: A | C5: Yangon | D5: Member | E5: Male | F5: Health and beauty | G5: 58.22 | H5: 8 | I5: 23.288 | J5: 489.048 | K5: 43492 | L5: 0.85625 | M5: Ewallet | N5: 465.76 | O5: 4.7619048 | P5: 23.288 | Q5: 8.4
A6: 373-73-7910 | B6: A | C6: Yangon | D6: Normal | E6: Male | F6: Sports and travel | G6: 86.31 | H6: 7 | I6: 30.2085 | J6: 634.3785 | K6: 43504 | L6: 0.44236111 | M6: Ewallet | N6: 604.17 | O6: 4.7619048 | P6: 30.2085 | Q6: 5.3
A7: 699-14-3026 | B7: C | C7: Naypyitaw | D7: Normal | E7: Male | F7: Electronic accessories | G7: 85.39 | H7: 7 | I7: 29.8865 | J7: 627.6165 | K7: 43549 | L7: 0.77083333 | M7: Ewallet | N7: 597.73 | O7: 4.7619048 | P7: 29.8865 | Q7: 4.1
A8: 355-53-5943 | B8: A | C8: Yangon | D8: Member | E8: Female | F8: Electronic accessories | G8: 68.84 | H8: 6 | I8: 20.652 | J8: 433.692 | K8: 43521 | L8: 0.60833333 | M8: Ewallet | N8: 413.04 | O8: 4.7619048 | P8: 20.652 | Q8: 5.8
A9: 315-22-5665 | B9: C | C9: Naypyitaw | D9: Normal | E9: Female | F9: Home and lifestyle | G9: 73.56 | H9: 10 | I9: 36.78 | J9: 772.38 | K9: 43520 | L9: 0.48472222 | M9: Ewallet | N9: 735.6 | O9: 4.7619048 | P9: 36.78 | Q9: 8
A10: 665-32-9167 | B10: A | C10: Yangon | D10: Member | E10: Female | F10: Health and beauty | G10: 36.26 | H10: 2 | I10: 3.626 | J10: 76.146 | K10: 43475 | L10: 0.71875 | M10: Credit card | N10: 72.52 | O10: 4.7619048 | P10: 3.626 | Q10: 7.2
A11: 692-92-5582 | B11: B | C11: Mandalay | D11: Member | E11: Female | F11: Food and beverages | G11: 54.84 | H11: 3 | I11: 8.226 | J11: 172.746 | K11: 43516 | L11: 0.56041667 | M11: Credit card | N11: 164.52 | O11: 4.7619048 | P11: 8.226 | Q11: 5.9
A12: 351-62-0822 | B12: B | C12: Mandalay | D12: Member | E12: Female | F12: Fashion accessories | G12: 14.48 | H12: 4 | I12: 2.896 | J12: 60.816 | K12: 43502 | L12: 0.75486111 | M12: Ewallet | N12: 57.92 | O12: 4.7619048 | P12: 2.896 | Q12: 4.5
A13: 529-56-3974 | B13: B | C13: Mandalay | D13: Member | E13: Male | F13: Electronic accessories | G13: 25.51 | H13: 4 | I13: 5.102 | J13: 107.142 | K13: 43533 | L13: 0.71041667 | M13: Cash | N13: 102.04 | O13: 4.7619048 | P13: 5.102 | Q13: 6.8
... A1001: 849-09-3807 | B1001: A | C1001: Yangon | D1001: Member | E1001: Female | F1001: Fashion accessories | G1001: 88.34 | H1001: 7 | I1001: 30.919 | J1001: 649.299 | K1001: 43514 | L1001: 0.56111111 | M1001: Cash | N1001: 618.38 | O1001: 4.7619048 | P1001: 30.919 | Q1001: 6.6

Sheet Analysis
A1: KPI | B1: VALUE | E1: Month | F1: Transactions | G1: Revenue | H1: Quantity
A2: Total Revenue | B2: =SUM('Source Data'!J2:J1001) -> 322966.75 | E2: January | F2: 352 | G2: 116291.87 | H2: 1965
A3: Total COGS | B3: =SUM('Source Data'!N2:N1001) -> 307587.38 | E3: February | F3: 303 | G3: 97219.37 | H3: 1654
A4: Gross Income | B4: =SUM('Source Data'!P2:P1001) -> 15379.369 | E4: March | F4: 345 | G4: 109455.51 | H4: 1891
A5: Total Quantity Sold | B5: =SUM('Source Data'!H2:H1001) -> 5510
A6: Number of Transactions | B6: =COUNTA('Source Data'!A2:A1001) -> 1000 | E6: Gender | F6: Revenue | G6: Quantity | H6: Transactions
A7: Average Transaction Value | B7: =B2/B6 -> 322.96675 | E7: Female | F7: =GETPIVOTDATA("[Measures].[Sum of Total]",'Pivot-Gender'!$A$3,"[Range].[Gender]","[Range].[Gender].&[Female]") -> 167882.92 | G7: =GETPIVOTDATA("[Measures].[Sum of Quantity]",'Pivot-Gender'!$A$3,"[Range].[Gender]","[Range].[Gender].&[Female]") -> 2869 | H7: =GETPIVOTDATA("[Measures].[Count of Invoice ID]",'Pivot-Gender'!$A$3,"[Range].[Gender]","[Range].[Gender].&[Female]") -> 501
A8: Overall Rating | B8: =GETPIVOTDATA("[Measures].[Average of Rating]",'Pivot-Product Line '!$A$3) -> 6.9727 | E8: Male | F8: =GETPIVOTDATA("[Measures].[Sum of Total]",'Pivot-Gender'!$A$3,"[Range].[Gender]","[Range].[Gender].&[Male]") -> 155083.82 | G8: =GETPIVOTDATA("[Measures].[Sum of Quantity]",'Pivot-Gender'!$A$3,"[Range].[Gender]","[Range].[Gender].&[Male]") -> 2641 | H8: =GETPIVOTDATA("[Measures].[Count of Invoice ID]",'Pivot-Gender'!$A$3,"[Range].[Gender]","[Range].[Gender].&[Male]") -> 499
A10: Branch | B10: Revenue | C10: Revenue Share % | D10: Gross Income | F10: Customer Type | G10: Revenue | H10: Quantity | I10: Transactions | J10: Gross Income
A11: A | B11: =GETPIVOTDATA("[Measures].[Sum of Total]",'Pivot-Branch'!$A$3,"[Range].[Branch]","[Range].[Branch].&[A]") -> 106200.37 | C11: =B11/$B$2 -> 0.32882757 | D11: =GETPIVOTDATA("[Measures].[Sum of gross income]",'Pivot-Branch'!$A$3,"[Range].[Branch]","[Range].[Branch].&[A]") -> 5057.1605 | F11: Member | G11: =GETPIVOTDATA("[Measures].[Sum of Total]",'Pivot-Customer'!$A$3,"[Range].[Customer type]","[Range].[Customer type].&[Member]") -> 164223.44 | H11: =GETPIVOTDATA("[Measures].[Sum of Quantity]",'Pivot-Customer'!$D$3,"[Range].[Customer type]","[Range].[Customer type].&[Member]") -> 2785 | I11: =GETPIVOTDATA("[Measures].[Count of Invoice ID]",'Pivot-Customer'!$A$3,"[Range].[Customer type]","[Range].[Customer type].&[Member]") -> 501 | J11: =GETPIVOTDATA("[Measures].[Sum of gross income]",'Pivot-Customer'!$A$3,"[Range].[Customer type]","[Range].[Customer type].&[Member]") -> 7820.164
A12: B | B12: =GETPIVOTDATA("[Measures].[Sum of Total]",'Pivot-Branch'!$A$3,"[Range].[Branch]","[Range].[Branch].&[B]") -> 106197.67 | C12: =B12/$B$2 -> 0.32881921 | D12: =GETPIVOTDATA("[Measures].[Sum of gross income]",'Pivot-Branch'!$A$3,"[Range].[Branch]","[Range].[Branch].&[B]") -> 5057.032 | F12: Normal | G12: =GETPIVOTDATA("[Measures].[Sum of Total]",'Pivot-Customer'!$A$3,"[Range].[Customer type]","[Range].[Customer type].&[Normal]") -> 158743.3 | H12: =GETPIVOTDATA("[Measures].[Sum of Quantity]",'Pivot-Customer'!$D$3,"[Range].[Customer type]","[Range].[Customer type].&[Normal]") -> 2725 | I12: =GETPIVOTDATA("[Measures].[Count of Invoice ID]",'Pivot-Customer'!$A$3,"[Range].[Customer type]","[Range].[Customer type].&[Normal]") -> 499 | J12: =GETPIVOTDATA("[Measures].[Sum of gross income]",'Pivot-Customer'!$A$3,"[Range].[Customer type]","[Range].[Customer type].&[Normal]") -> 7559.205
A13: C | B13: =GETPIVOTDATA("[Measures].[Sum of Total]",'Pivot-Branch'!$A$3,"[Range].[Branch]","[Range].[Branch].&[C]") -> 110568.71 | C13: =B13/$B$2 -> 0.34235322 | D13: =GETPIVOTDATA("[Measures].[Sum of gross income]",'Pivot-Branch'!$A$3,"[Range].[Branch]","[Range].[Branch].&[C]") -> 5265.1765
E14: Product Line | F14: Revenue | G14: Quantity | H14: Gross Income | I14: Transactions | J14: Revenue per Transaction
A15: Payment Method | B15: Transactions | C15: Revenue | E15: Electronic accessories | F15: =GETPIVOTDATA("[Measures].[Sum of Total]",'Pivot-Product Line '!$A$3,"[Range].[Product line]","[Range].[Product line].&[Electronic accessories]") -> 54337.531 | G15: =GETPIVOTDATA("[Measures].[Sum of Quantity]",'Pivot-Product Line '!$A$3,"[Range].[Product line]","[Range].[Product line].&[Electronic accessories]") -> 971 | H15: =GETPIVOTDATA("[Measures].[Sum of gross income]",'Pivot-Product Line '!$A$3,"[Range].[Product line]","[Range].[Product line].&[Electronic accessories]") -> 2587.5015 | I15: =GETPIVOTDATA("[Measures].[Count of Invoice ID]",'Pivot-Product Line '!$A$3,"[Range].[Product line]","[Range].[Product line].&[Electronic accessories]") -> 170 | J15: =F15/I15 -> 319.63254
A16: Cash | B16: =GETPIVOTDATA("[Measures].[Count of Invoice ID]",'Pivot-Payment'!$A$3,"[Range].[Payment]","[Range].[Payment].&[Cash]") -> 344 | C16: =GETPIVOTDATA("[Measures].[Sum of Total]",'Pivot-Payment'!$A$3,"[Range].[Payment]","[Range].[Payment].&[Cash]") -> 112206.57 | E16: Fashion accessories | F16: =GETPIVOTDATA("[Measures].[Sum of Total]",'Pivot-Product Line '!$A$3,"[Range].[Product line]","[Range].[Product line].&[Fashion accessories]") -> 54305.895 | G16: =GETPIVOTDATA("[Measures].[Sum of Quantity]",'Pivot-Product Line '!$A$3,"[Range].[Product line]","[Range].[Product line].&[Fashion accessories]") -> 902 | H16: =GETPIVOTDATA("[Measures].[Sum of gross income]",'Pivot-Product Line '!$A$3,"[Range].[Product line]","[Range].[Product line].&[Fashion accessories]") -> 2585.995 | I16: =GETPIVOTDATA("[Measures].[Count of Invoice ID]",'Pivot-Product Line '!$A$3,"[Range].[Product line]","[Range].[Product line].&[Fashion accessories]") -> 178 | J16: =F16/I16 -> 305.0893
A17: Credit Card | B17: =GETPIVOTDATA("[Measures].[Count of Invoice ID]",'Pivot-Payment'!$A$3,"[Range].[Payment]","[Range].[Payment].&[Credit card]") -> 311 | C17: =GETPIVOTDATA("[Measures].[Sum of Total]",'Pivot-Payment'!$A$3,"[Range].[Payment]","[Range].[Payment].&[Credit card]") -> 100767.07 | E17: Food and beverages | F17: =GETPIVOTDATA("[Measures].[Sum of Total]",'Pivot-Product Line '!$A$3,"[Range].[Product line]","[Range].[Product line].&[Food and beverages]") -> 56144.844 | G17: =GETPIVOTDATA("[Measures].[Sum of Quantity]",'Pivot-Product Line '!$A$3,"[Range].[Product line]","[Range].[Product line].&[Food and beverages]") -> 952 | H17: =GETPIVOTDATA("[Measures].[Sum of gross income]",'Pivot-Product Line '!$A$3,"[Range].[Product line]","[Range].[Product line].&[Food and beverages]") -> 2673.564 | I17: =GETPIVOTDATA("[Measures].[Count of Invoice ID]",'Pivot-Product Line '!$A$3,"[Range].[Product line]","[Range].[Product line].&[Food and beverages]") -> 174 | J17: =F17/I17 -> 322.67152
A18: E-wallet | B18: =GETPIVOTDATA("[Measures].[Count of Invoice ID]",'Pivot-Payment'!$A$3,"[Range].[Payment]","[Range].[Payment].&[Ewallet]") -> 345 | C18: =GETPIVOTDATA("[Measures].[Sum of Total]",'Pivot-Payment'!$A$3,"[Range].[Payment]","[Range].[Payment].&[Ewallet]") -> 109993.11 | E18: Health and beauty | F18: =GETPIVOTDATA("[Measures].[Sum of Total]",'Pivot-Product Line '!$A$3,"[Range].[Product line]","[Range].[Product line].&[Health and beauty]") -> 49193.739 | G18: =GETPIVOTDATA("[Measures].[Sum of Quantity]",'Pivot-Product Line '!$A$3,"[Range].[Product line]","[Range].[Product line].&[Health and beauty]") -> 854 | H18: =GETPIVOTDATA("[Measures].[Sum of gross income]",'Pivot-Product Line '!$A$3,"[Range].[Product line]","[Range].[Product line].&[Health and beauty]") -> 2342.559 | I18: =GETPIVOTDATA("[Measures].[Count of Invoice ID]",'Pivot-Product Line '!$A$3,"[Range].[Product line]","[Range].[Product line].&[Health and beauty]") -> 152 | J18: =F18/I18 -> 323.64302
E19: Home and lifestyle | F19: =GETPIVOTDATA("[Measures].[Sum of Total]",'Pivot-Product Line '!$A$3,"[Range].[Product line]","[Range].[Product line].&[Home and lifestyle]") -> 53861.913 | G19: =GETPIVOTDATA("[Measures].[Sum of Quantity]",'Pivot-Product Line '!$A$3,"[Range].[Product line]","[Range].[Product line].&[Home and lifestyle]") -> 911 | H19: =GETPIVOTDATA("[Measures].[Sum of gross income]",'Pivot-Product Line '!$A$3,"[Range].[Product line]","[Range].[Product line].&[Home and lifestyle]") -> 2564.853 | I19: =GETPIVOTDATA("[Measures].[Count of Invoice ID]",'Pivot-Product Line '!$A$3,"[Range].[Product line]","[Range].[Product line].&[Home and lifestyle]") -> 160 | J19: =F19/I19 -> 336.63696
E20: Sports and travel | F20: =GETPIVOTDATA("[Measures].[Sum of Total]",'Pivot-Product Line '!$A$3,"[Range].[Product line]","[Range].[Product line].&[Sports and travel]") -> 55122.827 | G20: =GETPIVOTDATA("[Measures].[Sum of Quantity]",'Pivot-Product Line '!$A$3,"[Range].[Product line]","[Range].[Product line].&[Sports and travel]") -> 920 | H20: =GETPIVOTDATA("[Measures].[Sum of gross income]",'Pivot-Product Line '!$A$3,"[Range].[Product line]","[Range].[Product line].&[Sports and travel]") -> 2624.8965 | I20: =GETPIVOTDATA("[Measures].[Count of Invoice ID]",'Pivot-Product Line '!$A$3,"[Range].[Product line]","[Range].[Product line].&[Sports and travel]") -> 166 | J20: =F20/I20 -> 332.06522
A23: Category | B23: Revenue | C23: Transactions | D23: Avg Transaction Value | F23: Category | G23: Revenue | H23: Transactions | I23: Avg Transaction Value
A24: Branch A | B24: 106200.37 | C24: 340 | D24: =B24/C24 -> 312.35403 | F24: Member | G24: 164223.44 | H24: 501 | I24: =G24/H24 -> 327.79131
A25: Branch B | B25: 106197.67 | C25: 332 | D25: =B25/C25 -> 319.8725 | F25: Normal | G25: 158743.3 | H25: 499 | I25: =G25/H25 -> 318.12286
A26: Branch C | B26: 110568.71 | C26: 328 | D26: =B26/C26 -> 337.09973
A28: Category | B28: Revenue | C28: Transactions | D28: Avg Transaction Value
A29: Female | B29: 167882.92 | C29: 501 | D29: =B29/C29 -> 335.09566
A30: Male | B30: 155083.82 | C30: 499 | D30: =B30/C30 -> 310.78923

Sheet Management Summary
A1: SUPERMARKET SALES ANALYSIS — MANAGEMENT SUMMARY
A3: KPI | B3: VALUE
A4: Total Revenue | B4: =SUM('Source Data'!J2:J1001) -> 322966.75
A5: Total COGS | B5: =SUM('Source Data'!N2:N1001) -> 307587.38
A6: Gross Income | B6: =SUM('Source Data'!P2:P1001) -> 15379.369
A7: Total Quantity Sold | B7: =SUM('Source Data'!H2:H1001) -> 5510
A8: Number of Transactions | B8: =COUNTA('Source Data'!A2:A1001) -> 1000
A9: Average Transaction Value | B9: =B4/B8 -> 322.96675
A10: Overall Rating | B10: =Analysis!B8 -> 6.9727
A13: Branch | B13: Revenue | C13: Revenue Share %
A14: A | B14: =GETPIVOTDATA("[Measures].[Sum of Total]",'Pivot-Branch'!$A$3,"[Range].[Branch]","[Range].[Branch].&[A]") -> 106200.37 | C14: =B14/$B$4 -> 0.32882757
A15: B | B15: =GETPIVOTDATA("[Measures].[Sum of Total]",'Pivot-Branch'!$A$3,"[Range].[Branch]","[Range].[Branch].&[B]") -> 106197.67 | C15: =B15/$B$4 -> 0.32881921
A16: C | B16: =GETPIVOTDATA("[Measures].[Sum of Total]",'Pivot-Branch'!$A$3,"[Range].[Branch]","[Range].[Branch].&[C]") -> 110568.71 | C16: =B16/$B$4 -> 0.34235322
A18: MANAGEMENT FINDINGS
A20: 1. Branch Performance
A21: Branch C generated the highest revenue at ₦110,568.71, representing 34.2% of total revenue.
A23: 2. Product Performance
A24: Food and Beverages generated the highest revenue at ₦56,144.84 and also recorded the highest average customer rating of 7.11.
A26: 3. Customer Type
A27: Members generated slightly higher revenue than customers recorded as Normal: ₦164,223.44 vs ₦158,743.31.
A29: 4. Gender Performance
A30: Female customers generated higher revenue than male customers: ₦167,882.93 vs ₦155,083.82.
A32: 5. Payment Methods
A33: E-wallet recorded the most transactions (345), while Cash generated the highest revenue (₦112,206.57).
A35: 6. Monthly Performance
... A40: Transaction volume does not always correspond directly with revenue. For example, Yangon recorded the highest number of transactions (340), while Naypyitaw generated the highest revenue (₦110,568.71).

Sheet Dashboard
G1: SUPERMARKET SALES PERFORMANCE DASHBOARD
J2: Q1 2019 | January – March
B4: TOTAL REVENUE | E4: GROSS INCOME | H4: TRANSACTION COUNT | K4: QUANTITY SOLD | N4: AVG. TRANSACTION VALUE | Q4: OVERALL RATING
B5: ='Management Summary'!B4 -> 322966.75 | E5: ='Management Summary'!B6 -> 15379.369 | H5: ='Management Summary'!B8 -> 1000 | K5: ='Management Summary'!B7 -> 5510 | N5: ='Management Summary'!B9 -> 322.96675 | Q5: ='Management Summary'!B10 -> 6.9727
B37: KEY TAKEAWAYS
B38: • Branch Performance: Branch C generated the highest revenue at ₦110,568.71, representing 34.2% of total revenue. • Product Performance: Food and Beverages generated the highest revenue at ₦56,144.84 and also recorded the highest average rating at 7.11. • Monthly Performance: January generated the highest monthly revenue at ₦116,291.87, while February recorded the lowest at ₦97,219.37. • Payment Behavior: E-wallet recorded the highest number of transactions (345), while Cash generated the highest revenue (₦112,206.57).

Sheet Business Insights
D1: SUPERMARKET SALES ANALYSIS — BUSINESS INSIGHTS
G2: Q1 2019 | January – March
B4: Insight 1 — Overall Performance | I4: Insight 2 — Branch Performance
B5: • The supermarket generated total revenue of ₦322,966.75 from 1,000 transactions, with 5,510 units sold. Gross income was ₦15,379.37, while the average transaction value was ₦322.97. • The results provide a baseline for comparing branch, product, customer, payment and monthly performance during the quarter. | I5: • Branch C generated the highest revenue at ₦110,568.71, accounting for 34.2% of total revenue. Branch A and Branch B generated ₦106,200.37 and ₦106,197.67, respectively. • Branch C achieved the highest revenue despite recording the lowest transaction count among the three branches. Its average transaction value was ₦337.10, compared with ₦312.35 for Branch A and ₦319.87 for Branch B.
B14: Insight 3 — Product Performance | I14: Insight 4 — Customer Performance
B15: • Food and Beverages generated the highest revenue at ₦56,144.84 and also recorded the highest gross income at ₦2,673.56. • Food and Beverages also recorded the highest average customer rating at 7.11, compared with the overall average rating of 6.97. • Electronic Accessories recorded the highest quantity sold at 971 units, while Fashion Accessories recorded the highest number of transactions at 178. | I15: • Customers recorded as Member generated ₦164,223.44 in revenue compared with ₦158,743.31 from customers recorded as Normal. • Members also recorded a higher average transaction value of ₦327.79, compared with ₦318.12 for Normal customers. • Female customers generated ₦167,882.93 in revenue compared with ₦155,083.82 from male customers. Their average transaction value was also higher at ₦335.10, compared with ₦310.79 for male customers.
B27: Insight 5 — Payment Behaviour | I27: Insight 6 —Monthly Performance
B28: • E-wallet recorded the highest transaction count at 345, followed closely by Cash at 344, while Credit Card recorded 311 transactions. • Despite having fewer transactions than E-wallet, Cash generated the highest revenue at ₦112,206.57. | I28: • January generated the highest revenue at ₦116,291.87 from 352 transactions. • Revenue declined to ₦97,219.37 in February before increasing to ₦109,455.51 in March. • February therefore represents the weakest revenue month within the quarter and may warrant further investigation into the factors affecting sales performance.
D39: BUSINESS RECOMMENDATIONS
B41: 1. Review Branch C's performance drivers. Management should investigate the factors contributing to Branch C's higher average transaction value and revenue. Practices identified at Branch C could be assessed for possible application across other branches. 2. Maintain focus on Food and Beverages. Food and Beverages generated the highest revenue and gross income while also recording the highest average customer rating. Management should monitor inventory availability and customer demand for this product line to avoid missed sales opportunities. 3. Investigate the February revenue decline. February generated the lowest monthly revenue at ₦97,219.37. Management should review factors such as product availability, promotions, customer traffic and operational issues to understand the decline. 4. Monitor payment-channel performance. E-wallet recorded the highest transaction count, while Cash generated the highest revenue. Management should monitor transaction value and customer usage across payment methods before making decisions about payment-channel priorities. 5. Review Health and Beauty performance. Health and Beauty recorded the lowest product-line revenue at ₦49,193.74 and the lowest quantity sold at 854 units. Management should investigate demand, pricing, product availability and customer feedback to identify potential improvement opportunities.

Sheet Pivot-Branch
A3: Row Labels | B3: Sum of Total | C3: Sum of gross income
A4: A | B4: 106200.37 | C4: 5057.1605
A5: B | B5: 106197.67 | C5: 5057.032
A6: C | B6: 110568.71 | C6: 5265.1765
A7: Grand Total | B7: 322966.75 | C7: 15379.369

Sheet Pivot-Customer
A3: Row Labels | B3: Count of Invoice ID | C3: Sum of gross income | D3: Sum of Total | E3: Sum of Quantity
A4: Member | B4: 501 | C4: 7820.164 | D4: 164223.44 | E4: 2785
A5: Normal | B5: 499 | C5: 7559.205 | D5: 158743.3 | E5: 2725
A6: Grand Total | B6: 1000 | C6: 15379.369 | D6: 322966.75 | E6: 5510

Sheet Pivot-Product Line 
A3: Row Labels | B3: Count of Invoice ID | C3: Sum of Total | D3: Sum of gross income | E3: Sum of Quantity | F3: Average of Rating
A4: Electronic accessories | B4: 170 | C4: 54337.531 | D4: 2587.5015 | E4: 971 | F4: 6.9247059
A5: Fashion accessories | B5: 178 | C5: 54305.895 | D5: 2585.995 | E5: 902 | F5: 7.0292135
A6: Food and beverages | B6: 174 | C6: 56144.844 | D6: 2673.564 | E6: 952 | F6: 7.1132184
A7: Health and beauty | B7: 152 | C7: 49193.739 | D7: 2342.559 | E7: 854 | F7: 7.0032895
A8: Home and lifestyle | B8: 160 | C8: 53861.913 | D8: 2564.853 | E8: 911 | F8: 6.8375
A9: Sports and travel | B9: 166 | C9: 55122.827 | D9: 2624.8965 | E9: 920 | F9: 6.9162651
A10: Grand Total | B10: 1000 | C10: 322966.75 | D10: 15379.369 | E10: 5510 | F10: 6.9727

Sheet Pivot-Payment
A3: Row Labels | B3: Count of Invoice ID | C3: Sum of Total
A4: Cash | B4: 344 | C4: 112206.57
A5: Credit card | B5: 311 | C5: 100767.07
A6: Ewallet | B6: 345 | C6: 109993.11
A7: Grand Total | B7: 1000 | C7: 322966.75

Sheet Pivot-Gender
A3: Row Labels | B3: Count of Invoice ID | C3: Sum of Total | D3: Sum of Quantity
A4: Female | B4: 501 | C4: 167882.92 | D4: 2869
A5: Male | B5: 499 | C5: 155083.82 | D5: 2641
A6: Grand Total | B6: 1000 | C6: 322966.75 | D6: 5510
